[
  {"phrase": "cotton", "meaning": "棉花；棉布", "example": "My **cotton** shirt is very comfortable in summer."},
  {"phrase": "cough", "meaning": "咳嗽", "example": "I have a bad **cough** and need to drink hot water."},
  {"phrase": "couldn", "meaning": "不能（couldn't的缩写）", "example": "I **couldn't** finish my homework last night."},
  {"phrase": "count", "meaning": "数数；计算", "example": "Please **count** the books on the desk."},
  {"phrase": "countable", "meaning": "可数的", "example": "'Book' is a **countable** noun."},
  {"phrase": "countries", "meaning": "国家（复数）", "example": "There are many **countries** in the world."},
  {"phrase": "country", "meaning": "国家；乡村", "example": "China is a great **country**."},
  {"phrase": "couplets", "meaning": "对联", "example": "People put red **couplets** on doors during Spring Festival."},
  {"phrase": "course", "meaning": "课程；过程", "example": "English is an important **course** in our school."},
  {"phrase": "cousin", "meaning": "堂（表）兄弟姐妹", "example": "My **cousin** will visit me this weekend."},
  {"phrase": "cover", "meaning": "覆盖；封面", "example": "Please **cover** the food with a plate."},
  {"phrase": "cream", "meaning": "奶油；乳霜", "example": "I like ice **cream** very much."},
  {"phrase": "cries", "meaning": "哭泣（第三人称单数）", "example": "The baby **cries** when she is hungry."},
  {"phrase": "crossword", "meaning": "纵横字谜", "example": "Let's do the **crossword** puzzle together."},
  {"phrase": "cucumber", "meaning": "黄瓜", "example": "I eat a **cucumber** every day for lunch."},
  {"phrase": "cucumbers", "meaning": "黄瓜（复数）", "example": "These **cucumbers** are fresh and delicious."},
  {"phrase": "cuisines", "meaning": "菜肴；烹饪（复数）", "example": "Chinese **cuisines** are famous all over the world."},
  {"phrase": "culture", "meaning": "文化", "example": "We should learn about different **culture**."},
  {"phrase": "cultures", "meaning": "文化（复数）", "example": "Different **cultures** have different traditions."},
  {"phrase": "cups", "meaning": "杯子（复数）", "example": "Please wash the **cups** after dinner."},
  {"phrase": "curd", "meaning": "凝乳；豆腐", "example": "Bean **curd** is my favorite food."},
  {"phrase": "cute", "meaning": "可爱的", "example": "The **cute** cat makes me happy."},
  {"phrase": "cuts", "meaning": "切；剪（第三人称单数）", "example": "She **cuts** the paper into small pieces."},
  {"phrase": "cutting", "meaning": "切割；剪裁", "example": "Be careful when **cutting** vegetables."},
  {"phrase": "dads", "meaning": "爸爸们（复数）", "example": "All the **dads** came to the school meeting."},
  {"phrase": "daily", "meaning": "每天的；日常的", "example": "I practice English **daily** for 30 minutes."},
  {"phrase": "daisy", "meaning": "雏菊", "example": "There is a beautiful **daisy** in the garden."},
  {"phrase": "dance", "meaning": "跳舞；舞蹈", "example": "Can you **dance** with me at the party?"},
  {"phrase": "dancer", "meaning": "舞者", "example": "My sister wants to be a **dancer**."},
  {"phrase": "dances", "meaning": "跳舞（第三人称单数）", "example": "She **dances** very well at the school show."},
  {"phrase": "dancing", "meaning": "跳舞", "example": "They are **dancing** to the music in the classroom."},
  {"phrase": "daniel", "meaning": "丹尼尔（人名）", "example": "**Daniel** is my best friend in class."},
  {"phrase": "dark", "meaning": "黑暗的；深色的", "example": "It's too **dark** in the room. Please turn on the light."},
  {"phrase": "date", "meaning": "日期；约会", "example": "What's the **date** today?"},
  {"phrase": "dates", "meaning": "日期（复数）；枣", "example": "I remember all the important **dates**."},
  {"phrase": "david", "meaning": "大卫（人名）", "example": "**David** plays basketball very well."},
  {"phrase": "days", "meaning": "天；日子（复数）", "example": "We have five school **days** every week."},
  {"phrase": "dead", "meaning": "死的；枯萎的", "example": "The **dead** leaves fall from the trees."},
  {"phrase": "deal", "meaning": "处理；交易", "example": "How do you **deal** with this problem?"},
  {"phrase": "dear", "meaning": "亲爱的；昂贵的", "example": "Dear mom, I miss you very much."},
  {"phrase": "december", "meaning": "十二月", "example": "**December** is the last month of the year."},
  {"phrase": "decide", "meaning": "决定", "example": "I **decide** to study hard this term."},
  {"phrase": "decorate", "meaning": "装饰", "example": "We **decorate** our classroom for New Year."},
  {"phrase": "decorations", "meaning": "装饰品（复数）", "example": "The Christmas **decorations** look beautiful."},
  {"phrase": "dekret", "meaning": "法令；判决", "example": "The king made a new **dekret** for the people."},
  {"phrase": "deli", "meaning": "熟食店", "example": "I bought some sandwiches at the **deli**."},
  {"phrase": "delicious", "meaning": "美味的", "example": "The cake tastes very **delicious**."},
  {"phrase": "demz", "meaning": "词汇（可能是专有名词）", "example": "Do you know the meaning of **demz**?"},
  {"phrase": "deni", "meaning": "丹妮（人名）", "example": "**Deni** is a new student in our class."},
  {"phrase": "denmark", "meaning": "丹麦", "example": "**Denmark** is a beautiful country in Europe."}
]
